qptools/__init__.py
qptools/core.cpython-312-darwin.so
qptools/cuda.py
qptools-1.0.3.dist-info/LICENSE
qptools-1.0.3.dist-info/METADATA
qptools-1.0.3.dist-info/WHEEL
qptools-1.0.3.dist-info/top_level.txt
qptools-1.0.3.dist-info/RECORD
